recipe/simple_use_case/async_demo.py
recipe/simple_use_case/sync_demo.py
scripts/performance_test.py
tests/test_async_simple_storage_manager.py
tests/test_client.py
tests/test_controller.py
tests/test_controller_data_partitions.py
tests/test_kv_storage_manager.py
tests/test_metadata.py
tests/test_ray_p2p.py
tests/test_samplers.py
tests/test_serial_utils_on_cpu.py
tests/test_simple_storage_unit.py
tests/test_storage_client_factory.py
transfer_queue/__init__.py
transfer_queue/client.py
transfer_queue/controller.py
transfer_queue/metadata.py
transfer_queue/sampler/__init__.py
transfer_queue/sampler/base.py
transfer_queue/sampler/grpo_group_n_sampler.py
transfer_queue/sampler/sequential_sampler.py
transfer_queue/storage/__init__.py
transfer_queue/storage/simple_backend.py
transfer_queue/storage/clients/__init__.py
transfer_queue/storage/clients/base.py
transfer_queue/storage/clients/factory.py
transfer_queue/storage/clients/mooncake_client.py
transfer_queue/storage/clients/ray_storage_client.py
transfer_queue/storage/clients/yuanrong_client.py
transfer_queue/storage/managers/__init__.py
transfer_queue/storage/managers/base.py
transfer_queue/storage/managers/factory.py
transfer_queue/storage/managers/mooncake_manager.py
transfer_queue/storage/managers/simple_backend_manager.py
transfer_queue/storage/managers/yuanrong_manager.py
transfer_queue/utils/__init__.py
transfer_queue/utils/perf_utils.py
transfer_queue/utils/serial_utils.py
transfer_queue/utils/utils.py
transfer_queue/utils/zmq_utils.py
transfer_queue/version/version
transferqueue-0.1.5.dist-info/licenses/LICENSE
tutorial/01_core_components.py
tutorial/02_metadata_concepts.py
tutorial/03_understanding_controller.py
tutorial/04_custom_sampler.py
transferqueue-0.1.5.dist-info/METADATA
transferqueue-0.1.5.dist-info/WHEEL
transferqueue-0.1.5.dist-info/top_level.txt
transferqueue-0.1.5.dist-info/RECORD
