Metadata-Version: 2.4
Name: TransferQueue
Version: 0.1.5
Summary: TransferQueue: An Asynchronous Streaming Data Management Module
Author-email: The TransferQueue Team <hanzy19@tsinghua.org.cn>
License: Apache-2.0
Requires-Python: >=3.10
License-File: LICENSE
Requires-Dist: ray[default]
Requires-Dist: tensordict>=0.10.0
Requires-Dist: pyzmq
Requires-Dist: hydra-core
Requires-Dist: numpy<2.0.0
Requires-Dist: msgspec
Requires-Dist: psutil
Provides-Extra: test
Requires-Dist: pytest>=7.0.0; extra == "test"
Requires-Dist: pytest-asyncio>=0.20.0; extra == "test"
Dynamic: license-file
